bonsai_dataio-4.8.19.dist-info/licenses/LICENSE.txt
config/airflow_attributes.config.json
config/data_attributes.config.yaml
config/readme.md
dataio/__init__.py
dataio/_classifications_helper.py
dataio/_plot.py
dataio/arg_parser.py
dataio/config.py
dataio/default.py
dataio/load.py
dataio/resources.py
dataio/save.py
dataio/set_logger.py
dataio/tools.py
dataio/validate.py
dataio/_export/readme.txt
dataio/_export/ermodel/backup.dataio.yaml
dataio/_export/ermodel/ermodel.py
dataio/_export/ermodel/data/conc_concordance.csv
dataio/_export/ermodel/data/dim_dimension.csv
dataio/_export/ermodel/data/ermodel.dataio.yaml
dataio/_export/ermodel/data/fact_fact.csv
dataio/_export/ermodel/data/tree_tree.csv
dataio/_export/task/task.dataio.yaml
dataio/_export/task/task.py
dataio/_export/task/lookup/conc_concordance.csv
dataio/_export/task/lookup/dim_level.csv
dataio/_export/task/lookup/lookup.dataio.png
dataio/_export/task/lookup/lookup.dataio.yaml
dataio/_export/task/lookup/lookup.validate.yaml
dataio/_export/task/lookup/tree_alternative.csv
dataio/_export/task/lookup/tree_main.csv
dataio/schemas/__init__.py
dataio/schemas/base_models.py
dataio/schemas/bonsai_api/PPF_fact_schemas_samples.py
dataio/schemas/bonsai_api/PPF_fact_schemas_uncertainty.py
dataio/schemas/bonsai_api/__init__.py
dataio/schemas/bonsai_api/admin.py
dataio/schemas/bonsai_api/base_models.py
dataio/schemas/bonsai_api/correspondences.py
dataio/schemas/bonsai_api/dims.py
dataio/schemas/bonsai_api/external_schemas.py
dataio/schemas/bonsai_api/facts.py
dataio/schemas/bonsai_api/ipcc.py
dataio/schemas/bonsai_api/matrix.py
dataio/schemas/bonsai_api/metadata.py
dataio/schemas/bonsai_api/uncertainty.py
dataio/utils/__init__.py
dataio/utils/accounts.py
dataio/utils/connectors.py
dataio/utils/path_manager.py
dataio/utils/schema_enums.py
dataio/utils/versions.py
dataio/utils/hsut/__init__.py
dataio/utils/hsut/io.py
dataio/utils/hsut/resources_hsut.py
bonsai_dataio-4.8.19.dist-info/METADATA
bonsai_dataio-4.8.19.dist-info/WHEEL
bonsai_dataio-4.8.19.dist-info/entry_points.txt
bonsai_dataio-4.8.19.dist-info/top_level.txt
bonsai_dataio-4.8.19.dist-info/RECORD
