Metadata-Version: 2.4
Name: bonsai_dataio
Version: 4.8.19
Summary: "Python package dataio of the util workflow stage of the BONSAI database"
Home-page: https://gitlab.com/bonsamurais/bonsai/util/dataio
Author: admin_bonsai
Author-email: admin.gettingthedataright@aau.dk
License: MIT
Project-URL: Documentation, https://bonsamurais.gitlab.io/bonsai/util/dataio
Platform: any
Classifier: Development Status :: 4 - Beta
Classifier: Programming Language :: Python
License-File: LICENSE.txt
Requires-Dist: importlib-metadata
Requires-Dist: pandas
Requires-Dist: numpy<2.0
Requires-Dist: h5py
Requires-Dist: tables
Requires-Dist: pint
Requires-Dist: pyyaml>=6.0.1
Requires-Dist: frictionless[pandas]>=5.15.10
Requires-Dist: graphviz>=0.20.1
Requires-Dist: pydantic[email]>=2.9.1
Requires-Dist: python-dotenv
Requires-Dist: semantic_version
Requires-Dist: currencyconverter
Requires-Dist: bonsai_classifications
Provides-Extra: testing
Requires-Dist: setuptools>=65.6.3; extra == "testing"
Requires-Dist: pytest>=7.2.2; extra == "testing"
Requires-Dist: pytest-cov>=4.0.0; extra == "testing"
Requires-Dist: importlib_resources; extra == "testing"
Requires-Dist: anytree; extra == "testing"
Requires-Dist: tox; extra == "testing"
Dynamic: license-file
